LICENSE
MANIFEST.in
README.rst
requirements.txt
setup.py
combo/__init__.py
combo/version.py
combo.egg-info/PKG-INFO
combo.egg-info/SOURCES.txt
combo.egg-info/dependency_links.txt
combo.egg-info/requires.txt
combo.egg-info/top_level.txt
combo/models/__init__.py
combo/models/base.py
combo/models/classifier_comb.py
combo/models/classifier_dcs.py
combo/models/classifier_des.py
combo/models/classifier_stacking.py
combo/models/cluster_comb.py
combo/models/cluster_eac.py
combo/models/detector_comb.py
combo/models/detector_lscp.py
combo/models/score_comb.py
combo/models/sklearn_base.py
combo/utils/__init__.py
combo/utils/data.py
combo/utils/example.py
combo/utils/utility.py