Metadata-Version: 2.1
Name: combo
Version: 0.1.3
Summary: A Python Toolbox for Machine Learning Model Combination
Home-page: https://github.com/yzhao062/combo
Author: Yue Zhao
Author-email: zhaoy@cmu.edu
License: UNKNOWN
Download-URL: https://github.com/yzhao062/combo/archive/master.zip
Keywords: ensemble learning,model combination,outlier ensembles,data mining,machine learning,clustering,python
Platform: UNKNOWN
Classifier: Development Status :: 2 - Pre-Alpha
Classifier: Intended Audience :: Education
Classifier: Intended Audience :: Financial and Insurance Industry
Classifier: Intended Audience :: Science/Research
Classifier: Intended Audience :: Developers
Classifier: Intended Audience :: Information Technology
Classifier: License :: OSI Approved :: BSD License
Classifier: Programming Language :: Python :: 3.5
Classifier: Programming Language :: Python :: 3.6
Classifier: Programming Language :: Python :: 3.7
License-File: LICENSE
